CHANGES.txt
COPYING.txt
MANIFEST.in
README.rst
TODO.txt
install.rst
readme.rst
run_tests.py
setup.cfg
setup.py
docs/Makefile
docs/make.bat
docs/build/doctrees/environment.pickle
docs/build/doctrees/index.doctree
docs/build/doctrees/newsletterapp.doctree
docs/build/doctrees/project.doctree
docs/build/html/.buildinfo
docs/build/html/genindex.html
docs/build/html/index.html
docs/build/html/newsletterapp.html
docs/build/html/objects.inv
docs/build/html/project.html
docs/build/html/search.html
docs/build/html/searchindex.js
docs/build/html/_sources/index.txt
docs/build/html/_sources/newsletterapp.txt
docs/build/html/_sources/project.txt
docs/build/html/_static/ajax-loader.gif
docs/build/html/_static/basic.css
docs/build/html/_static/comment-bright.png
docs/build/html/_static/comment-close.png
docs/build/html/_static/comment.png
docs/build/html/_static/default.css
docs/build/html/_static/doctools.js
docs/build/html/_static/down-pressed.png
docs/build/html/_static/down.png
docs/build/html/_static/file.png
docs/build/html/_static/jquery.js
docs/build/html/_static/minus.png
docs/build/html/_static/plus.png
docs/build/html/_static/pygments.css
docs/build/html/_static/searchtools.js
docs/build/html/_static/sidebar.js
docs/build/html/_static/underscore.js
docs/build/html/_static/up-pressed.png
docs/build/html/_static/up.png
docs/build/html/_static/websupport.js
docs/source/conf.py
docs/source/index.rst
docs/source/newsletterapp.rst
docs/source/project.rst
newsletter/__init__.py
newsletter.egg-info/PKG-INFO
newsletter.egg-info/SOURCES.txt
newsletter.egg-info/dependency_links.txt
newsletter.egg-info/not-zip-safe
newsletter.egg-info/requires.txt
newsletter.egg-info/top_level.txt
newsletter/base/__init__.py
newsletter/base/base.py
newsletter/base/base_test.py
newsletter/newsletterapp/__init__.py
newsletter/newsletterapp/newsletterapp.ini
newsletter/newsletterapp/newsletterapp.py
newsletter/newsletterapp/readme.rst
newsletter/newsletterapp/test_newsletterapp.py
newsletter/newsletterapp/docs/Makefile
newsletter/newsletterapp/docs/make.bat
newsletter/newsletterapp/docs/build/doctrees/environment.pickle
newsletter/newsletterapp/docs/build/doctrees/index.doctree
